clickzetta/bulkload/__init__.py
clickzetta/bulkload/bulkload_api.py
clickzetta/bulkload/bulkload_enums.py
clickzetta/bulkload/bulkload_session.py
clickzetta/bulkload/bulkload_stream.py
clickzetta/bulkload/bulkload_writer.py
clickzetta/bulkload/cz_oss_filesystem.py
clickzetta/bulkload/cz_table.py
clickzetta/bulkload/version.py
clickzetta/bulkload/_proto/account_pb2.py
clickzetta/bulkload/_proto/account_pb2_grpc.py
clickzetta/bulkload/_proto/block_bloom_filter_pb2.py
clickzetta/bulkload/_proto/block_bloom_filter_pb2_grpc.py
clickzetta/bulkload/_proto/bucket_info_pb2.py
clickzetta/bulkload/_proto/bucket_info_pb2_grpc.py
clickzetta/bulkload/_proto/compression_pb2.py
clickzetta/bulkload/_proto/compression_pb2_grpc.py
clickzetta/bulkload/_proto/connection_meta_pb2.py
clickzetta/bulkload/_proto/connection_meta_pb2_grpc.py
clickzetta/bulkload/_proto/data_type_pb2.py
clickzetta/bulkload/_proto/data_type_pb2_grpc.py
clickzetta/bulkload/_proto/expression_pb2.py
clickzetta/bulkload/_proto/expression_pb2_grpc.py
clickzetta/bulkload/_proto/file_format_type_pb2.py
clickzetta/bulkload/_proto/file_format_type_pb2_grpc.py
clickzetta/bulkload/_proto/file_meta_data_pb2.py
clickzetta/bulkload/_proto/file_meta_data_pb2_grpc.py
clickzetta/bulkload/_proto/file_system_pb2.py
clickzetta/bulkload/_proto/file_system_pb2_grpc.py
clickzetta/bulkload/_proto/function_meta_pb2.py
clickzetta/bulkload/_proto/function_meta_pb2_grpc.py
clickzetta/bulkload/_proto/hash_pb2.py
clickzetta/bulkload/_proto/hash_pb2_grpc.py
clickzetta/bulkload/_proto/ingestion_pb2.py
clickzetta/bulkload/_proto/ingestion_pb2_grpc.py
clickzetta/bulkload/_proto/input_split_pb2.py
clickzetta/bulkload/_proto/input_split_pb2_grpc.py
clickzetta/bulkload/_proto/job_meta_pb2.py
clickzetta/bulkload/_proto/job_meta_pb2_grpc.py
clickzetta/bulkload/_proto/job_result_cache_meta_pb2.py
clickzetta/bulkload/_proto/job_result_cache_meta_pb2_grpc.py
clickzetta/bulkload/_proto/kudu_common_pb2.py
clickzetta_ingestion_python-0.8.83.dist-info/LICENSE
clickzetta_ingestion_python-0.8.83.dist-info/METADATA
clickzetta_ingestion_python-0.8.83.dist-info/WHEEL
clickzetta_ingestion_python-0.8.83.dist-info/top_level.txt
clickzetta_ingestion_python-0.8.83.dist-info/RECORD
